[{"job_name": "S5-RA001-S310-Sm-27", "GB": "S5-RA001-S310", "element": "Sm", "site": "27", "Z": 62, "n_Fe": 79, "n_Fe_diff": 0.0, "energy": -636.99245942, "energy_zero": -636.98465224, "Eseg": 1.8346158699999933, "scf_steps": 82.0, "convergence": true, "element_count": 52, "potcar_electron_count": 8.0, "total_electron_count": 648.0, "method": "KP", "state": "Unrelaxed", "defect_type": "Substitutional", "dataset_case": "KP_Unrelaxed_Substitutional", "dataset_id": "fe_x_gb_kp_unrelaxed", "dataset_name": "Fe-X GB Segregation (KP, Unrelaxed)", "dataset_category": "Fe-X GB Segregation"}, {"job_name": "S5-RA001-S310-Sm-33", "GB": "S5-RA001-S310", "element": "Sm", "site": "33", "Z": 62, "n_Fe": 79, "n_Fe_diff": 0.0, "energy": -637.45564219, "energy_zero": -637.44504131, "Eseg": 1.3714330999999902, "scf_steps": 62.0, "convergence": true, "element_count": 46, "potcar_electron_count": 8.0, "total_electron_count": 648.0, "method": "KP", "state": "Unrelaxed", "defect_type": "Substitutional", "dataset_case": "KP_Unrelaxed_Substitutional", "dataset_id": "fe_x_gb_kp_unrelaxed", "dataset_name": "Fe-X GB Segregation (KP, Unrelaxed)", "dataset_category": "Fe-X GB Segregation"}, {"job_name": "S5-RA001-S310-Sm-37", "GB": "S5-RA001-S310", "element": "Sm", "site": "37", "Z": 62, "n_Fe": 79, "n_Fe_diff": 0.0, "energy": -639.18039893, "energy_zero": -639.17611533, "Eseg": -0.35332363999998506, "scf_steps": 87.0, "convergence": true, "element_count": 42, "potcar_electron_count": 8.0, "total_electron_count": 648.0, "method": "KP", "state": "Unrelaxed", "defect_type": "Substitutional", "dataset_case": "KP_Unrelaxed_Substitutional", "dataset_id": "fe_x_gb_kp_unrelaxed", "dataset_name": "Fe-X GB Segregation (KP, Unrelaxed)", "dataset_category": "Fe-X GB Segregation"}, {"job_name": "S5-RA001-S310-Sm-23", "GB": "S5-RA001-S310", "element": "Sm", "site": "23", "Z": 62, "n_Fe": 79, "n_Fe_diff": 0.0, "energy": -638.07054077, "energy_zero": -638.05756897, "Eseg": 0.7565345200000593, "scf_steps": 64.0, "convergence": true, "element_count": 56, "potcar_electron_count": 8.0, "total_electron_count": 648.0, "method": "KP", "state": "Unrelaxed", "defect_type": "Substitutional", "dataset_case": "KP_Unrelaxed_Substitutional", "dataset_id": "fe_x_gb_kp_unrelaxed", "dataset_name": "Fe-X GB Segregation (KP, Unrelaxed)", "dataset_category": "Fe-X GB Segregation"}, {"job_name": "S5-RA001-S310-Sm-40", "GB": "S5-RA001-S310", "element": "Sm", "site": "40", "Z": 62, "n_Fe": 79, "n_Fe_diff": 0.0, "energy": -639.39818976, "energy_zero": -639.39163573, "Eseg": -0.5711144699999977, "scf_steps": 60.0, "convergence": true, "element_count": 39, "potcar_electron_count": 8.0, "total_electron_count": 648.0, "method": "KP", "state": "Unrelaxed", "defect_type": "Substitutional", "dataset_case": "KP_Unrelaxed_Substitutional", "dataset_id": "fe_x_gb_kp_unrelaxed", "dataset_name": "Fe-X GB Segregation (KP, Unrelaxed)", "dataset_category": "Fe-X GB Segregation"}, {"job_name": "S5-RA001-S210-Sm-35", "GB": "S5-RA001-S210", "element": "Sm", "site": "35", "Z": 62, "n_Fe": 75, "n_Fe_diff": 0.0, "energy": -612.211531, "energy_zero": -612.20203586, "Eseg": -0.39272104999997737, "scf_steps": 63.0, "convergence": true, "element_count": 40, "potcar_electron_count": 8.0, "total_electron_count": 616.0, "method": "KP", "state": "Unrelaxed", "defect_type": "Substitutional", "dataset_case": "KP_Unrelaxed_Substitutional", "dataset_id": "fe_x_gb_kp_unrelaxed", "dataset_name": "Fe-X GB Segregation (KP, Unrelaxed)", "dataset_category": "Fe-X GB Segregation"}, {"job_name": "S5-RA001-S210-Sm-24", "GB": "S5-RA001-S210", "element": "Sm", "site": "24", "Z": 62, "n_Fe": 75, "n_Fe_diff": 0.0, "energy": -611.25661596, "energy_zero": -611.2478834, "Eseg": 0.5621939900000825, "scf_steps": 234.0, "convergence": true, "element_count": 51, "potcar_electron_count": 8.0, "total_electron_count": 616.0, "method": "KP", "state": "Unrelaxed", "defect_type": "Substitutional", "dataset_case": "KP_Unrelaxed_Substitutional", "dataset_id": "fe_x_gb_kp_unrelaxed", "dataset_name": "Fe-X GB Segregation (KP, Unrelaxed)", "dataset_category": "Fe-X GB Segregation"}, {"job_name": "S5-RA001-S210-Sm-27", "GB": "S5-RA001-S210", "element": "Sm", "site": "27", "Z": 62, "n_Fe": 75, "n_Fe_diff": 0.0, "energy": -611.5325922, "energy_zero": -611.52578203, "Eseg": 0.2862177500001053, "scf_steps": 72.0, "convergence": true, "element_count": 48, "potcar_electron_count": 8.0, "total_electron_count": 616.0, "method": "KP", "state": "Unrelaxed", "defect_type": "Substitutional", "dataset_case": "KP_Unrelaxed_Substitutional", "dataset_id": "fe_x_gb_kp_unrelaxed", "dataset_name": "Fe-X GB Segregation (KP, Unrelaxed)", "dataset_category": "Fe-X GB Segregation"}, {"job_name": "S5-RA001-S210-Sm-29", "GB": "S5-RA001-S210", "element": "Sm", "site": "29", "Z": 62, "n_Fe": 75, "n_Fe_diff": 0.0, "energy": -610.96250517, "energy_zero": -610.95409173, "Eseg": 0.8563047800000732, "scf_steps": 98.0, "convergence": true, "element_count": 46, "potcar_electron_count": 8.0, "total_electron_count": 616.0, "method": "KP", "state": "Unrelaxed", "defect_type": "Substitutional", "dataset_case": "KP_Unrelaxed_Substitutional", "dataset_id": "fe_x_gb_kp_unrelaxed", "dataset_name": "Fe-X GB Segregation (KP, Unrelaxed)", "dataset_category": "Fe-X GB Segregation"}, {"job_name": "S5-RA001-S210-Sm-37", "GB": "S5-RA001-S210", "element": "Sm", "site": "37", "Z": 62, "n_Fe": 75, "n_Fe_diff": 0.0, "energy": -613.44184289, "energy_zero": -613.43329481, "Eseg": -1.6230329399999164, "scf_steps": 65.0, "convergence": true, "element_count": 38, "potcar_electron_count": 8.0, "total_electron_count": 616.0, "method": "KP", "state": "Unrelaxed", "defect_type": "Substitutional", "dataset_case": "KP_Unrelaxed_Substitutional", "dataset_id": "fe_x_gb_kp_unrelaxed", "dataset_name": "Fe-X GB Segregation (KP, Unrelaxed)", "dataset_category": "Fe-X GB Segregation"}, {"job_name": "S5-RA001-S210-Sm-31", "GB": "S5-RA001-S210", "element": "Sm", "site": "31", "Z": 62, "n_Fe": 75, "n_Fe_diff": 0.0, "energy": -611.51971988, "energy_zero": -611.51703909, "Eseg": 0.29909007000003385, "scf_steps": 78.0, "convergence": true, "element_count": 44, "potcar_electron_count": 8.0, "total_electron_count": 616.0, "method": "KP", "state": "Unrelaxed", "defect_type": "Substitutional", "dataset_case": "KP_Unrelaxed_Substitutional", "dataset_id": "fe_x_gb_kp_unrelaxed", "dataset_name": "Fe-X GB Segregation (KP, Unrelaxed)", "dataset_category": "Fe-X GB Segregation"}, {"job_name": "S5-RA001-S210-Sm-33", "GB": "S5-RA001-S210", "element": "Sm", "site": "33", "Z": 62, "n_Fe": 75, "n_Fe_diff": 0.0, "energy": -611.18611884, "energy_zero": -611.17678953, "Eseg": 0.6326911100001098, "scf_steps": 92.0, "convergence": true, "element_count": 42, "potcar_electron_count": 8.0, "total_electron_count": 616.0, "method": "KP", "state": "Unrelaxed", "defect_type": "Substitutional", "dataset_case": "KP_Unrelaxed_Substitutional", "dataset_id": "fe_x_gb_kp_unrelaxed", "dataset_name": "Fe-X GB Segregation (KP, Unrelaxed)", "dataset_category": "Fe-X GB Segregation"}, {"job_name": "S11-RA110-S3-32-Sm-18", "GB": "S11-RA110-S3-32", "element": "Sm", "site": "18", "Z": 62, "n_Fe": 41, "n_Fe_diff": 0.0, "energy": -338.35341393, "energy_zero": -338.34455248, "Eseg": 0.6385349100000894, "scf_steps": 77.0, "convergence": true, "element_count": 23, "potcar_electron_count": 8.0, "total_electron_count": 344.0, "method": "KP", "state": "Unrelaxed", "defect_type": "Substitutional", "dataset_case": "KP_Unrelaxed_Substitutional", "dataset_id": "fe_x_gb_kp_unrelaxed", "dataset_name": "Fe-X GB Segregation (KP, Unrelaxed)", "dataset_category": "Fe-X GB Segregation"}, {"job_name": "S11-RA110-S3-32-Sm-20", "GB": "S11-RA110-S3-32", "element": "Sm", "site": "20", "Z": 62, "n_Fe": 41, "n_Fe_diff": 0.0, "energy": -338.42988553, "energy_zero": -338.4206598, "Eseg": 0.5620633100000987, "scf_steps": 62.0, "convergence": true, "element_count": 21, "potcar_electron_count": 8.0, "total_electron_count": 344.0, "method": "KP", "state": "Unrelaxed", "defect_type": "Substitutional", "dataset_case": "KP_Unrelaxed_Substitutional", "dataset_id": "fe_x_gb_kp_unrelaxed", "dataset_name": "Fe-X GB Segregation (KP, Unrelaxed)", "dataset_category": "Fe-X GB Segregation"}, {"job_name": "S11-RA110-S3-32-Sm-13", "GB": "S11-RA110-S3-32", "element": "Sm", "site": "13", "Z": 62, "n_Fe": 41, "n_Fe_diff": 0.0, "energy": -338.16814869, "energy_zero": -338.1579875, "Eseg": 0.8238001500000678, "scf_steps": 64.0, "convergence": true, "element_count": 28, "potcar_electron_count": 8.0, "total_electron_count": 344.0, "method": "KP", "state": "Unrelaxed", "defect_type": "Substitutional", "dataset_case": "KP_Unrelaxed_Substitutional", "dataset_id": "fe_x_gb_kp_unrelaxed", "dataset_name": "Fe-X GB Segregation (KP, Unrelaxed)", "dataset_category": "Fe-X GB Segregation"}, {"job_name": "S11-RA110-S3-32-Sm-17", "GB": "S11-RA110-S3-32", "element": "Sm", "site": "17", "Z": 62, "n_Fe": 41, "n_Fe_diff": 0.0, "energy": -335.34318084, "energy_zero": -335.33455086, "Eseg": 3.648768000000075, "scf_steps": 260.0, "convergence": true, "element_count": 24, "potcar_electron_count": 8.0, "total_electron_count": 344.0, "method": "KP", "state": "Unrelaxed", "defect_type": "Substitutional", "dataset_case": "KP_Unrelaxed_Substitutional", "dataset_id": "fe_x_gb_kp_unrelaxed", "dataset_name": "Fe-X GB Segregation (KP, Unrelaxed)", "dataset_category": "Fe-X GB Segregation"}, {"job_name": "S11-RA110-S3-32-Sm-11", "GB": "S11-RA110-S3-32", "element": "Sm", "site": "11", "Z": 62, "n_Fe": 41, "n_Fe_diff": 0.0, "energy": -338.14418025, "energy_zero": -338.13532872, "Eseg": 0.8477685900001006, "scf_steps": 117.0, "convergence": true, "element_count": 30, "potcar_electron_count": 8.0, "total_electron_count": 344.0, "method": "KP", "state": "Unrelaxed", "defect_type": "Substitutional", "dataset_case": "KP_Unrelaxed_Substitutional", "dataset_id": "fe_x_gb_kp_unrelaxed", "dataset_name": "Fe-X GB Segregation (KP, Unrelaxed)", "dataset_category": "Fe-X GB Segregation"}, {"job_name": "S11-RA110-S3-32-Sm-15", "GB": "S11-RA110-S3-32", "element": "Sm", "site": "15", "Z": 62, "n_Fe": 41, "n_Fe_diff": 0.0, "energy": -338.25643645, "energy_zero": -338.24893481, "Eseg": 0.7355123900000535, "scf_steps": 68.0, "convergence": true, "element_count": 26, "potcar_electron_count": 8.0, "total_electron_count": 344.0, "method": "KP", "state": "Unrelaxed", "defect_type": "Substitutional", "dataset_case": "KP_Unrelaxed_Substitutional", "dataset_id": "fe_x_gb_kp_unrelaxed", "dataset_name": "Fe-X GB Segregation (KP, Unrelaxed)", "dataset_category": "Fe-X GB Segregation"}, {"job_name": "S11-RA110-S3-32-Sm-19", "GB": "S11-RA110-S3-32", "element": "Sm", "site": "19", "Z": 62, "n_Fe": 41, "n_Fe_diff": 0.0, "energy": -339.27310673, "energy_zero": -339.26123222, "Eseg": -0.28115788999991764, "scf_steps": 67.0, "convergence": true, "element_count": 22, "potcar_electron_count": 8.0, "total_electron_count": 344.0, "method": "KP", "state": "Unrelaxed", "defect_type": "Substitutional", "dataset_case": "KP_Unrelaxed_Substitutional", "dataset_id": "fe_x_gb_kp_unrelaxed", "dataset_name": "Fe-X GB Segregation (KP, Unrelaxed)", "dataset_category": "Fe-X GB Segregation"}, {"job_name": "S11-RA110-S3-32-Sm-12", "GB": "S11-RA110-S3-32", "element": "Sm", "site": "12", "Z": 62, "n_Fe": 41, "n_Fe_diff": 0.0, "energy": -338.10679239, "energy_zero": -338.09694408, "Eseg": 0.8851564500000677, "scf_steps": 69.0, "convergence": true, "element_count": 29, "potcar_electron_count": 8.0, "total_electron_count": 344.0, "method": "KP", "state": "Unrelaxed", "defect_type": "Substitutional", "dataset_case": "KP_Unrelaxed_Substitutional", "dataset_id": "fe_x_gb_kp_unrelaxed", "dataset_name": "Fe-X GB Segregation (KP, Unrelaxed)", "dataset_category": "Fe-X GB Segregation"}, {"job_name": "S11-RA110-S3-32-Sm-16", "GB": "S11-RA110-S3-32", "element": "Sm", "site": "16", "Z": 62, "n_Fe": 41, "n_Fe_diff": 0.0, "energy": -338.15031228, "energy_zero": -338.13765549, "Eseg": 0.8416365600000972, "scf_steps": 54.0, "convergence": true, "element_count": 25, "potcar_electron_count": 8.0, "total_electron_count": 344.0, "method": "KP", "state": "Unrelaxed", "defect_type": "Substitutional", "dataset_case": "KP_Unrelaxed_Substitutional", "dataset_id": "fe_x_gb_kp_unrelaxed", "dataset_name": "Fe-X GB Segregation (KP, Unrelaxed)", "dataset_category": "Fe-X GB Segregation"}, {"job_name": "S11-RA110-S3-32-Sm-21", "GB": "S11-RA110-S3-32", "element": "Sm", "site": "21", "Z": 62, "n_Fe": 41, "n_Fe_diff": 0.0, "energy": -338.51304506, "energy_zero": -338.50814461, "Eseg": 0.47890378000005285, "scf_steps": 61.0, "convergence": true, "element_count": 20, "potcar_electron_count": 8.0, "total_electron_count": 344.0, "method": "KP", "state": "Unrelaxed", "defect_type": "Substitutional", "dataset_case": "KP_Unrelaxed_Substitutional", "dataset_id": "fe_x_gb_kp_unrelaxed", "dataset_name": "Fe-X GB Segregation (KP, Unrelaxed)", "dataset_category": "Fe-X GB Segregation"}, {"job_name": "S11-RA110-S3-32-Sm-22", "GB": "S11-RA110-S3-32", "element": "Sm", "site": "22", "Z": 62, "n_Fe": 41, "n_Fe_diff": 0.0, "energy": -339.27526805, "energy_zero": -339.27134078, "Eseg": -0.2833192099999451, "scf_steps": 118.0, "convergence": true, "element_count": 19, "potcar_electron_count": 8.0, "total_electron_count": 344.0, "method": "KP", "state": "Unrelaxed", "defect_type": "Substitutional", "dataset_case": "KP_Unrelaxed_Substitutional", "dataset_id": "fe_x_gb_kp_unrelaxed", "dataset_name": "Fe-X GB Segregation (KP, Unrelaxed)", "dataset_category": "Fe-X GB Segregation"}, {"job_name": "S11-RA110-S3-32-Sm-14", "GB": "S11-RA110-S3-32", "element": "Sm", "site": "14", "Z": 62, "n_Fe": 41, "n_Fe_diff": 0.0, "energy": -338.11267965, "energy_zero": -338.10331283, "Eseg": 0.8792691900000591, "scf_steps": 63.0, "convergence": true, "element_count": 27, "potcar_electron_count": 8.0, "total_electron_count": 344.0, "method": "KP", "state": "Unrelaxed", "defect_type": "Substitutional", "dataset_case": "KP_Unrelaxed_Substitutional", "dataset_id": "fe_x_gb_kp_unrelaxed", "dataset_name": "Fe-X GB Segregation (KP, Unrelaxed)", "dataset_category": "Fe-X GB Segregation"}, {"job_name": "S3-RA110-S1-12-Sm-12", "GB": "S3-RA110-S1-12", "element": "Sm", "site": "12", "Z": 62, "n_Fe": 47, "n_Fe_diff": 0.0, "energy": -388.57994102, "energy_zero": -388.56814304, "Eseg": 1.1989841000000752, "scf_steps": 68.0, "convergence": true, "element_count": 35, "potcar_electron_count": 8.0, "total_electron_count": 392.0, "method": "KP", "state": "Unrelaxed", "defect_type": "Substitutional", "dataset_case": "KP_Unrelaxed_Substitutional", "dataset_id": "fe_x_gb_kp_unrelaxed", "dataset_name": "Fe-X GB Segregation (KP, Unrelaxed)", "dataset_category": "Fe-X GB Segregation"}, {"job_name": "S3-RA110-S1-12-Sm-14", "GB": "S3-RA110-S1-12", "element": "Sm", "site": "14", "Z": 62, "n_Fe": 47, "n_Fe_diff": 0.0, "energy": -388.61713563, "energy_zero": -388.60480721, "Eseg": 1.1617894900000465, "scf_steps": 79.0, "convergence": true, "element_count": 33, "potcar_electron_count": 8.0, "total_electron_count": 392.0, "method": "KP", "state": "Unrelaxed", "defect_type": "Substitutional", "dataset_case": "KP_Unrelaxed_Substitutional", "dataset_id": "fe_x_gb_kp_unrelaxed", "dataset_name": "Fe-X GB Segregation (KP, Unrelaxed)", "dataset_category": "Fe-X GB Segregation"}, {"job_name": "S3-RA110-S1-12-Sm-18", "GB": "S3-RA110-S1-12", "element": "Sm", "site": "18", "Z": 62, "n_Fe": 47, "n_Fe_diff": 0.0, "energy": -388.63977601, "energy_zero": -388.62215084, "Eseg": 1.1391491100000621, "scf_steps": 64.0, "convergence": true, "element_count": 29, "potcar_electron_count": 8.0, "total_electron_count": 392.0, "method": "KP", "state": "Unrelaxed", "defect_type": "Substitutional", "dataset_case": "KP_Unrelaxed_Substitutional", "dataset_id": "fe_x_gb_kp_unrelaxed", "dataset_name": "Fe-X GB Segregation (KP, Unrelaxed)", "dataset_category": "Fe-X GB Segregation"}, {"job_name": "S3-RA110-S1-12-Sm-24", "GB": "S3-RA110-S1-12", "element": "Sm", "site": "24", "Z": 62, "n_Fe": 47, "n_Fe_diff": 0.0, "energy": -389.17393616, "energy_zero": -389.16231269, "Eseg": 0.6049889600000711, "scf_steps": 58.0, "convergence": true, "element_count": 23, "potcar_electron_count": 8.0, "total_electron_count": 392.0, "method": "KP", "state": "Unrelaxed", "defect_type": "Substitutional", "dataset_case": "KP_Unrelaxed_Substitutional", "dataset_id": "fe_x_gb_kp_unrelaxed", "dataset_name": "Fe-X GB Segregation (KP, Unrelaxed)", "dataset_category": "Fe-X GB Segregation"}, {"job_name": "S3-RA110-S1-12-Sm-20", "GB": "S3-RA110-S1-12", "element": "Sm", "site": "20", "Z": 62, "n_Fe": 47, "n_Fe_diff": 0.0, "energy": -388.80749693, "energy_zero": -388.78992666, "Eseg": 0.9714281900000401, "scf_steps": 63.0, "convergence": true, "element_count": 27, "potcar_electron_count": 8.0, "total_electron_count": 392.0, "method": "KP", "state": "Unrelaxed", "defect_type": "Substitutional", "dataset_case": "KP_Unrelaxed_Substitutional", "dataset_id": "fe_x_gb_kp_unrelaxed", "dataset_name": "Fe-X GB Segregation (KP, Unrelaxed)", "dataset_category": "Fe-X GB Segregation"}, {"job_name": "S3-RA110-S1-12-Sm-16", "GB": "S3-RA110-S1-12", "element": "Sm", "site": "16", "Z": 62, "n_Fe": 47, "n_Fe_diff": 0.0, "energy": -388.61929153, "energy_zero": -388.60531752, "Eseg": 1.1596335900000554, "scf_steps": 72.0, "convergence": true, "element_count": 31, "potcar_electron_count": 8.0, "total_electron_count": 392.0, "method": "KP", "state": "Unrelaxed", "defect_type": "Substitutional", "dataset_case": "KP_Unrelaxed_Substitutional", "dataset_id": "fe_x_gb_kp_unrelaxed", "dataset_name": "Fe-X GB Segregation (KP, Unrelaxed)", "dataset_category": "Fe-X GB Segregation"}, {"job_name": "S3-RA110-S1-12-Sm-22", "GB": "S3-RA110-S1-12", "element": "Sm", "site": "22", "Z": 62, "n_Fe": 47, "n_Fe_diff": 0.0, "energy": -389.09423906, "energy_zero": -389.07926135, "Eseg": 0.6846860600000468, "scf_steps": 65.0, "convergence": true, "element_count": 25, "potcar_electron_count": 8.0, "total_electron_count": 392.0, "method": "KP", "state": "Unrelaxed", "defect_type": "Substitutional", "dataset_case": "KP_Unrelaxed_Substitutional", "dataset_id": "fe_x_gb_kp_unrelaxed", "dataset_name": "Fe-X GB Segregation (KP, Unrelaxed)", "dataset_category": "Fe-X GB Segregation"}, {"job_name": "S3-RA110-S1-11-Sm-36", "GB": "S3-RA110-S1-11", "element": "Sm", "site": "36", "Z": 62, "n_Fe": 71, "n_Fe_diff": 0.0, "energy": -582.46484297, "energy_zero": -582.44272303, "Eseg": -0.30252054999982647, "scf_steps": 66.0, "convergence": true, "element_count": 35, "potcar_electron_count": 8.0, "total_electron_count": 584.0, "method": "KP", "state": "Unrelaxed", "defect_type": "Substitutional", "dataset_case": "KP_Unrelaxed_Substitutional", "dataset_id": "fe_x_gb_kp_unrelaxed", "dataset_name": "Fe-X GB Segregation (KP, Unrelaxed)", "dataset_category": "Fe-X GB Segregation"}, {"job_name": "S3-RA110-S1-11-Sm-34", "GB": "S3-RA110-S1-11", "element": "Sm", "site": "34", "Z": 62, "n_Fe": 71, "n_Fe_diff": 0.0, "energy": -580.02297997, "energy_zero": -579.99700857, "Eseg": 2.139342450000072, "scf_steps": 94.0, "convergence": true, "element_count": 37, "potcar_electron_count": 8.0, "total_electron_count": 584.0, "method": "KP", "state": "Unrelaxed", "defect_type": "Substitutional", "dataset_case": "KP_Unrelaxed_Substitutional", "dataset_id": "fe_x_gb_kp_unrelaxed", "dataset_name": "Fe-X GB Segregation (KP, Unrelaxed)", "dataset_category": "Fe-X GB Segregation"}, {"job_name": "S3-RA110-S1-11-Sm-28", "GB": "S3-RA110-S1-11", "element": "Sm", "site": "28", "Z": 62, "n_Fe": 71, "n_Fe_diff": 0.0, "energy": -581.26095955, "energy_zero": -581.24779338, "Eseg": 0.9013628700000709, "scf_steps": 75.0, "convergence": true, "element_count": 43, "potcar_electron_count": 8.0, "total_electron_count": 584.0, "method": "KP", "state": "Unrelaxed", "defect_type": "Substitutional", "dataset_case": "KP_Unrelaxed_Substitutional", "dataset_id": "fe_x_gb_kp_unrelaxed", "dataset_name": "Fe-X GB Segregation (KP, Unrelaxed)", "dataset_category": "Fe-X GB Segregation"}, {"job_name": "S3-RA110-S1-11-Sm-24", "GB": "S3-RA110-S1-11", "element": "Sm", "site": "24", "Z": 62, "n_Fe": 71, "n_Fe_diff": 0.0, "energy": -581.14036473, "energy_zero": -581.1225594, "Eseg": 1.0219576900001357, "scf_steps": 65.0, "convergence": true, "element_count": 47, "potcar_electron_count": 8.0, "total_electron_count": 584.0, "method": "KP", "state": "Unrelaxed", "defect_type": "Substitutional", "dataset_case": "KP_Unrelaxed_Substitutional", "dataset_id": "fe_x_gb_kp_unrelaxed", "dataset_name": "Fe-X GB Segregation (KP, Unrelaxed)", "dataset_category": "Fe-X GB Segregation"}, {"job_name": "S3-RA110-S1-11-Sm-26", "GB": "S3-RA110-S1-11", "element": "Sm", "site": "26", "Z": 62, "n_Fe": 71, "n_Fe_diff": 0.0, "energy": -581.30400327, "energy_zero": -581.28869814, "Eseg": 0.8583191500001703, "scf_steps": 62.0, "convergence": true, "element_count": 45, "potcar_electron_count": 8.0, "total_electron_count": 584.0, "method": "KP", "state": "Unrelaxed", "defect_type": "Substitutional", "dataset_case": "KP_Unrelaxed_Substitutional", "dataset_id": "fe_x_gb_kp_unrelaxed", "dataset_name": "Fe-X GB Segregation (KP, Unrelaxed)", "dataset_category": "Fe-X GB Segregation"}, {"job_name": "S3-RA110-S1-11-Sm-30", "GB": "S3-RA110-S1-11", "element": "Sm", "site": "30", "Z": 62, "n_Fe": 71, "n_Fe_diff": 0.0, "energy": -581.2293625, "energy_zero": -581.2144256, "Eseg": 0.9329599200001439, "scf_steps": 64.0, "convergence": true, "element_count": 41, "potcar_electron_count": 8.0, "total_electron_count": 584.0, "method": "KP", "state": "Unrelaxed", "defect_type": "Substitutional", "dataset_case": "KP_Unrelaxed_Substitutional", "dataset_id": "fe_x_gb_kp_unrelaxed", "dataset_name": "Fe-X GB Segregation (KP, Unrelaxed)", "dataset_category": "Fe-X GB Segregation"}, {"job_name": "S3-RA110-S1-11-Sm-20", "GB": "S3-RA110-S1-11", "element": "Sm", "site": "20", "Z": 62, "n_Fe": 71, "n_Fe_diff": 0.0, "energy": -581.16776149, "energy_zero": -581.15278546, "Eseg": 0.9945609300001479, "scf_steps": 68.0, "convergence": true, "element_count": 51, "potcar_electron_count": 8.0, "total_electron_count": 584.0, "method": "KP", "state": "Unrelaxed", "defect_type": "Substitutional", "dataset_case": "KP_Unrelaxed_Substitutional", "dataset_id": "fe_x_gb_kp_unrelaxed", "dataset_name": "Fe-X GB Segregation (KP, Unrelaxed)", "dataset_category": "Fe-X GB Segregation"}, {"job_name": "S3-RA110-S1-11-Sm-32", "GB": "S3-RA110-S1-11", "element": "Sm", "site": "32", "Z": 62, "n_Fe": 71, "n_Fe_diff": 0.0, "energy": -582.26031643, "energy_zero": -582.24400538, "Eseg": -0.09799400999986574, "scf_steps": 67.0, "convergence": true, "element_count": 39, "potcar_electron_count": 8.0, "total_electron_count": 584.0, "method": "KP", "state": "Unrelaxed", "defect_type": "Substitutional", "dataset_case": "KP_Unrelaxed_Substitutional", "dataset_id": "fe_x_gb_kp_unrelaxed", "dataset_name": "Fe-X GB Segregation (KP, Unrelaxed)", "dataset_category": "Fe-X GB Segregation"}, {"job_name": "S3-RA110-S1-11-Sm-22", "GB": "S3-RA110-S1-11", "element": "Sm", "site": "22", "Z": 62, "n_Fe": 71, "n_Fe_diff": 0.0, "energy": -581.14023457, "energy_zero": -581.12629603, "Eseg": 1.0220878500001618, "scf_steps": 59.0, "convergence": true, "element_count": 49, "potcar_electron_count": 8.0, "total_electron_count": 584.0, "method": "KP", "state": "Unrelaxed", "defect_type": "Substitutional", "dataset_case": "KP_Unrelaxed_Substitutional", "dataset_id": "fe_x_gb_kp_unrelaxed", "dataset_name": "Fe-X GB Segregation (KP, Unrelaxed)", "dataset_category": "Fe-X GB Segregation"}, {"job_name": "S9-RA110-S2-21-Sm-35", "GB": "S9-RA110-S2-21", "element": "Sm", "site": "35", "Z": 62, "n_Fe": 67, "n_Fe_diff": 0.0, "energy": -550.76721124, "energy_zero": -550.75965845, "Eseg": -0.1710763799999313, "scf_steps": 68.0, "convergence": true, "element_count": 32, "potcar_electron_count": 8.0, "total_electron_count": 552.0, "method": "KP", "state": "Unrelaxed", "defect_type": "Substitutional", "dataset_case": "KP_Unrelaxed_Substitutional", "dataset_id": "fe_x_gb_kp_unrelaxed", "dataset_name": "Fe-X GB Segregation (KP, Unrelaxed)", "dataset_category": "Fe-X GB Segregation"}, {"job_name": "S9-RA110-S2-21-Sm-24", "GB": "S9-RA110-S2-21", "element": "Sm", "site": "24", "Z": 62, "n_Fe": 67, "n_Fe_diff": 0.0, "energy": -549.90664839, "energy_zero": -549.89437023, "Eseg": 0.6894864700001335, "scf_steps": 76.0, "convergence": true, "element_count": 43, "potcar_electron_count": 8.0, "total_electron_count": 552.0, "method": "KP", "state": "Unrelaxed", "defect_type": "Substitutional", "dataset_case": "KP_Unrelaxed_Substitutional", "dataset_id": "fe_x_gb_kp_unrelaxed", "dataset_name": "Fe-X GB Segregation (KP, Unrelaxed)", "dataset_category": "Fe-X GB Segregation"}, {"job_name": "S9-RA110-S2-21-Sm-28", "GB": "S9-RA110-S2-21", "element": "Sm", "site": "28", "Z": 62, "n_Fe": 67, "n_Fe_diff": 0.0, "energy": -550.01004098, "energy_zero": -549.9981878, "Eseg": 0.586093880000135, "scf_steps": 92.0, "convergence": true, "element_count": 39, "potcar_electron_count": 8.0, "total_electron_count": 552.0, "method": "KP", "state": "Unrelaxed", "defect_type": "Substitutional", "dataset_case": "KP_Unrelaxed_Substitutional", "dataset_id": "fe_x_gb_kp_unrelaxed", "dataset_name": "Fe-X GB Segregation (KP, Unrelaxed)", "dataset_category": "Fe-X GB Segregation"}, {"job_name": "S9-RA110-S2-21-Sm-26", "GB": "S9-RA110-S2-21", "element": "Sm", "site": "26", "Z": 62, "n_Fe": 67, "n_Fe_diff": 0.0, "energy": -548.76399857, "energy_zero": -548.74831433, "Eseg": 1.8321362900001077, "scf_steps": 108.0, "convergence": true, "element_count": 41, "potcar_electron_count": 8.0, "total_electron_count": 552.0, "method": "KP", "state": "Unrelaxed", "defect_type": "Substitutional", "dataset_case": "KP_Unrelaxed_Substitutional", "dataset_id": "fe_x_gb_kp_unrelaxed", "dataset_name": "Fe-X GB Segregation (KP, Unrelaxed)", "dataset_category": "Fe-X GB Segregation"}, {"job_name": "S9-RA110-S2-21-Sm-30", "GB": "S9-RA110-S2-21", "element": "Sm", "site": "30", "Z": 62, "n_Fe": 67, "n_Fe_diff": 0.0, "energy": -550.35322151, "energy_zero": -550.34233574, "Eseg": 0.2429133500000944, "scf_steps": 75.0, "convergence": true, "element_count": 37, "potcar_electron_count": 8.0, "total_electron_count": 552.0, "method": "KP", "state": "Unrelaxed", "defect_type": "Substitutional", "dataset_case": "KP_Unrelaxed_Substitutional", "dataset_id": "fe_x_gb_kp_unrelaxed", "dataset_name": "Fe-X GB Segregation (KP, Unrelaxed)", "dataset_category": "Fe-X GB Segregation"}, {"job_name": "S9-RA110-S2-21-Sm-29", "GB": "S9-RA110-S2-21", "element": "Sm", "site": "29", "Z": 62, "n_Fe": 67, "n_Fe_diff": 0.0, "energy": -550.30115428, "energy_zero": -550.29000539, "Eseg": 0.2949805800001286, "scf_steps": 67.0, "convergence": true, "element_count": 38, "potcar_electron_count": 8.0, "total_electron_count": 552.0, "method": "KP", "state": "Unrelaxed", "defect_type": "Substitutional", "dataset_case": "KP_Unrelaxed_Substitutional", "dataset_id": "fe_x_gb_kp_unrelaxed", "dataset_name": "Fe-X GB Segregation (KP, Unrelaxed)", "dataset_category": "Fe-X GB Segregation"}, {"job_name": "S9-RA110-S2-21-Sm-32", "GB": "S9-RA110-S2-21", "element": "Sm", "site": "32", "Z": 62, "n_Fe": 67, "n_Fe_diff": 0.0, "energy": -550.64239363, "energy_zero": -550.63275625, "Eseg": -0.046258769999894866, "scf_steps": 63.0, "convergence": true, "element_count": 35, "potcar_electron_count": 8.0, "total_electron_count": 552.0, "method": "KP", "state": "Unrelaxed", "defect_type": "Substitutional", "dataset_case": "KP_Unrelaxed_Substitutional", "dataset_id": "fe_x_gb_kp_unrelaxed", "dataset_name": "Fe-X GB Segregation (KP, Unrelaxed)", "dataset_category": "Fe-X GB Segregation"}, {"job_name": "S9-RA110-S2-21-Sm-34", "GB": "S9-RA110-S2-21", "element": "Sm", "site": "34", "Z": 62, "n_Fe": 67, "n_Fe_diff": 0.0, "energy": -552.4344002, "energy_zero": -552.4249356, "Eseg": -1.8382653399999072, "scf_steps": 72.0, "convergence": true, "element_count": 33, "potcar_electron_count": 8.0, "total_electron_count": 552.0, "method": "KP", "state": "Unrelaxed", "defect_type": "Substitutional", "dataset_case": "KP_Unrelaxed_Substitutional", "dataset_id": "fe_x_gb_kp_unrelaxed", "dataset_name": "Fe-X GB Segregation (KP, Unrelaxed)", "dataset_category": "Fe-X GB Segregation"}, {"job_name": "S9-RA110-S2-21-Sm-27", "GB": "S9-RA110-S2-21", "element": "Sm", "site": "27", "Z": 62, "n_Fe": 67, "n_Fe_diff": 0.0, "energy": -549.93361913, "energy_zero": -549.92123331, "Eseg": 0.6625157300001092, "scf_steps": 76.0, "convergence": true, "element_count": 40, "potcar_electron_count": 8.0, "total_electron_count": 552.0, "method": "KP", "state": "Unrelaxed", "defect_type": "Substitutional", "dataset_case": "KP_Unrelaxed_Substitutional", "dataset_id": "fe_x_gb_kp_unrelaxed", "dataset_name": "Fe-X GB Segregation (KP, Unrelaxed)", "dataset_category": "Fe-X GB Segregation"}, {"job_name": "S9-RA110-S2-21-Sm-25", "GB": "S9-RA110-S2-21", "element": "Sm", "site": "25", "Z": 62, "n_Fe": 67, "n_Fe_diff": 0.0, "energy": -549.94057394, "energy_zero": -549.92913196, "Eseg": 0.6555609200000845, "scf_steps": 57.0, "convergence": true, "element_count": 42, "potcar_electron_count": 8.0, "total_electron_count": 552.0, "method": "KP", "state": "Unrelaxed", "defect_type": "Substitutional", "dataset_case": "KP_Unrelaxed_Substitutional", "dataset_id": "fe_x_gb_kp_unrelaxed", "dataset_name": "Fe-X GB Segregation (KP, Unrelaxed)", "dataset_category": "Fe-X GB Segregation"}, {"job_name": "S9-RA110-S2-21-Sm-23", "GB": "S9-RA110-S2-21", "element": "Sm", "site": "23", "Z": 62, "n_Fe": 67, "n_Fe_diff": 0.0, "energy": -549.86126097, "energy_zero": -549.84992894, "Eseg": 0.7348738900001308, "scf_steps": 63.0, "convergence": true, "element_count": 44, "potcar_electron_count": 8.0, "total_electron_count": 552.0, "method": "KP", "state": "Unrelaxed", "defect_type": "Substitutional", "dataset_case": "KP_Unrelaxed_Substitutional", "dataset_id": "fe_x_gb_kp_unrelaxed", "dataset_name": "Fe-X GB Segregation (KP, Unrelaxed)", "dataset_category": "Fe-X GB Segregation"}, {"job_name": "S9-RA110-S2-21-Sm-33", "GB": "S9-RA110-S2-21", "element": "Sm", "site": "33", "Z": 62, "n_Fe": 67, "n_Fe_diff": 0.0, "energy": -548.99613362, "energy_zero": -548.97322819, "Eseg": 1.600001240000097, "scf_steps": 73.0, "convergence": true, "element_count": 34, "potcar_electron_count": 8.0, "total_electron_count": 552.0, "method": "KP", "state": "Unrelaxed", "defect_type": "Substitutional", "dataset_case": "KP_Unrelaxed_Substitutional", "dataset_id": "fe_x_gb_kp_unrelaxed", "dataset_name": "Fe-X GB Segregation (KP, Unrelaxed)", "dataset_category": "Fe-X GB Segregation"}, {"job_name": "S5-RA001-S310-Sm-27", "GB": "S5-RA001-S310", "element": "Sm", "site": "27", "Z": 62, "n_Fe": 79, "n_Fe_diff": 0.0, "energy": -639.01974674, "energy_zero": -639.01628467, "Eseg": -0.1926714499999207, "scf_steps": 72.0, "convergence": true, "element_count": 52, "potcar_electron_count": 8.0, "total_electron_count": 648.0, "method": "KP", "state": "Relaxed", "defect_type": "Substitutional", "dataset_case": "KP_Relaxed_Substitutional", "dataset_id": "fe_x_gb_kp_relaxed", "dataset_name": "Fe-X GB Segregation (KP, Relaxed)", "dataset_category": "Fe-X GB Segregation"}, {"job_name": "S5-RA001-S310-Sm-33", "GB": "S5-RA001-S310", "element": "Sm", "site": "33", "Z": 62, "n_Fe": 79, "n_Fe_diff": 0.0, "energy": -638.94901374, "energy_zero": -638.93194567, "Eseg": -0.12193845000001602, "scf_steps": 202.0, "convergence": true, "element_count": 46, "potcar_electron_count": 8.0, "total_electron_count": 648.0, "method": "KP", "state": "Relaxed", "defect_type": "Substitutional", "dataset_case": "KP_Relaxed_Substitutional", "dataset_id": "fe_x_gb_kp_relaxed", "dataset_name": "Fe-X GB Segregation (KP, Relaxed)", "dataset_category": "Fe-X GB Segregation"}, {"job_name": "S5-RA001-S310-Sm-37", "GB": "S5-RA001-S310", "element": "Sm", "site": "37", "Z": 62, "n_Fe": 79, "n_Fe_diff": 0.0, "energy": -640.74827018, "energy_zero": -640.74286138, "Eseg": -1.9211948899999243, "scf_steps": 106.0, "convergence": true, "element_count": 42, "potcar_electron_count": 8.0, "total_electron_count": 648.0, "method": "KP", "state": "Relaxed", "defect_type": "Substitutional", "dataset_case": "KP_Relaxed_Substitutional", "dataset_id": "fe_x_gb_kp_relaxed", "dataset_name": "Fe-X GB Segregation (KP, Relaxed)", "dataset_category": "Fe-X GB Segregation"}, {"job_name": "S5-RA001-S310-Sm-23", "GB": "S5-RA001-S310", "element": "Sm", "site": "23", "Z": 62, "n_Fe": 79, "n_Fe_diff": 0.0, "energy": -638.98234315, "energy_zero": -638.97981564, "Eseg": -0.15526785999998083, "scf_steps": 61.0, "convergence": true, "element_count": 56, "potcar_electron_count": 8.0, "total_electron_count": 648.0, "method": "KP", "state": "Relaxed", "defect_type": "Substitutional", "dataset_case": "KP_Relaxed_Substitutional", "dataset_id": "fe_x_gb_kp_relaxed", "dataset_name": "Fe-X GB Segregation (KP, Relaxed)", "dataset_category": "Fe-X GB Segregation"}, {"job_name": "S5-RA001-S310-Sm-40", "GB": "S5-RA001-S310", "element": "Sm", "site": "40", "Z": 62, "n_Fe": 79, "n_Fe_diff": 0.0, "energy": -639.50807435, "energy_zero": -639.50885235, "Eseg": -0.6809990599999765, "scf_steps": 198.0, "convergence": true, "element_count": 39, "potcar_electron_count": 8.0, "total_electron_count": 648.0, "method": "KP", "state": "Relaxed", "defect_type": "Substitutional", "dataset_case": "KP_Relaxed_Substitutional", "dataset_id": "fe_x_gb_kp_relaxed", "dataset_name": "Fe-X GB Segregation (KP, Relaxed)", "dataset_category": "Fe-X GB Segregation"}, {"job_name": "S5-RA001-S210-Sm-35", "GB": "S5-RA001-S210", "element": "Sm", "site": "35", "Z": 62, "n_Fe": 75, "n_Fe_diff": 0.0, "energy": -612.16700839, "energy_zero": -612.14450964, "Eseg": -0.3481984399999192, "scf_steps": 98.0, "convergence": true, "element_count": 40, "potcar_electron_count": 8.0, "total_electron_count": 616.0, "method": "KP", "state": "Relaxed", "defect_type": "Substitutional", "dataset_case": "KP_Relaxed_Substitutional", "dataset_id": "fe_x_gb_kp_relaxed", "dataset_name": "Fe-X GB Segregation (KP, Relaxed)", "dataset_category": "Fe-X GB Segregation"}, {"job_name": "S5-RA001-S210-Sm-24", "GB": "S5-RA001-S210", "element": "Sm", "site": "24", "Z": 62, "n_Fe": 75, "n_Fe_diff": 0.0, "energy": -611.00216283, "energy_zero": -610.9965178, "Eseg": 0.8166471200000842, "scf_steps": 60.0, "convergence": true, "element_count": 51, "potcar_electron_count": 8.0, "total_electron_count": 616.0, "method": "KP", "state": "Relaxed", "defect_type": "Substitutional", "dataset_case": "KP_Relaxed_Substitutional", "dataset_id": "fe_x_gb_kp_relaxed", "dataset_name": "Fe-X GB Segregation (KP, Relaxed)", "dataset_category": "Fe-X GB Segregation"}, {"job_name": "S5-RA001-S210-Sm-27", "GB": "S5-RA001-S210", "element": "Sm", "site": "27", "Z": 62, "n_Fe": 75, "n_Fe_diff": 0.0, "energy": -612.49922849, "energy_zero": -612.49288923, "Eseg": -0.6804185399998914, "scf_steps": 57.0, "convergence": true, "element_count": 48, "potcar_electron_count": 8.0, "total_electron_count": 616.0, "method": "KP", "state": "Relaxed", "defect_type": "Substitutional", "dataset_case": "KP_Relaxed_Substitutional", "dataset_id": "fe_x_gb_kp_relaxed", "dataset_name": "Fe-X GB Segregation (KP, Relaxed)", "dataset_category": "Fe-X GB Segregation"}, {"job_name": "S5-RA001-S210-Sm-29", "GB": "S5-RA001-S210", "element": "Sm", "site": "29", "Z": 62, "n_Fe": 75, "n_Fe_diff": 0.0, "energy": -613.74513899, "energy_zero": -613.73856739, "Eseg": -1.9263290399999278, "scf_steps": 68.0, "convergence": true, "element_count": 46, "potcar_electron_count": 8.0, "total_electron_count": 616.0, "method": "KP", "state": "Relaxed", "defect_type": "Substitutional", "dataset_case": "KP_Relaxed_Substitutional", "dataset_id": "fe_x_gb_kp_relaxed", "dataset_name": "Fe-X GB Segregation (KP, Relaxed)", "dataset_category": "Fe-X GB Segregation"}, {"job_name": "S5-RA001-S210-Sm-37", "GB": "S5-RA001-S210", "element": "Sm", "site": "37", "Z": 62, "n_Fe": 75, "n_Fe_diff": 0.0, "energy": -614.07198821, "energy_zero": -614.06184291, "Eseg": -2.2531782599999133, "scf_steps": 72.0, "convergence": true, "element_count": 38, "potcar_electron_count": 8.0, "total_electron_count": 616.0, "method": "KP", "state": "Relaxed", "defect_type": "Substitutional", "dataset_case": "KP_Relaxed_Substitutional", "dataset_id": "fe_x_gb_kp_relaxed", "dataset_name": "Fe-X GB Segregation (KP, Relaxed)", "dataset_category": "Fe-X GB Segregation"}, {"job_name": "S5-RA001-S210-Sm-31", "GB": "S5-RA001-S210", "element": "Sm", "site": "31", "Z": 62, "n_Fe": 75, "n_Fe_diff": 0.0, "energy": -614.04386523, "energy_zero": -614.03850059, "Eseg": -2.2250552799999923, "scf_steps": 61.0, "convergence": true, "element_count": 44, "potcar_electron_count": 8.0, "total_electron_count": 616.0, "method": "KP", "state": "Relaxed", "defect_type": "Substitutional", "dataset_case": "KP_Relaxed_Substitutional", "dataset_id": "fe_x_gb_kp_relaxed", "dataset_name": "Fe-X GB Segregation (KP, Relaxed)", "dataset_category": "Fe-X GB Segregation"}, {"job_name": "S5-RA001-S210-Sm-33", "GB": "S5-RA001-S210", "element": "Sm", "site": "33", "Z": 62, "n_Fe": 75, "n_Fe_diff": 0.0, "energy": -614.00604188, "energy_zero": -613.99521286, "Eseg": -2.187231929999939, "scf_steps": 142.0, "convergence": true, "element_count": 42, "potcar_electron_count": 8.0, "total_electron_count": 616.0, "method": "KP", "state": "Relaxed", "defect_type": "Substitutional", "dataset_case": "KP_Relaxed_Substitutional", "dataset_id": "fe_x_gb_kp_relaxed", "dataset_name": "Fe-X GB Segregation (KP, Relaxed)", "dataset_category": "Fe-X GB Segregation"}, {"job_name": "S11-RA110-S3-32-Sm-18", "GB": "S11-RA110-S3-32", "element": "Sm", "site": "18", "Z": 62, "n_Fe": 41, "n_Fe_diff": 0.0, "energy": -340.5810838, "energy_zero": -340.57179083, "Eseg": -1.5891349599999103, "scf_steps": 64.0, "convergence": true, "element_count": 23, "potcar_electron_count": 8.0, "total_electron_count": 344.0, "method": "KP", "state": "Relaxed", "defect_type": "Substitutional", "dataset_case": "KP_Relaxed_Substitutional", "dataset_id": "fe_x_gb_kp_relaxed", "dataset_name": "Fe-X GB Segregation (KP, Relaxed)", "dataset_category": "Fe-X GB Segregation"}, {"job_name": "S11-RA110-S3-32-Sm-20", "GB": "S11-RA110-S3-32", "element": "Sm", "site": "20", "Z": 62, "n_Fe": 41, "n_Fe_diff": 0.0, "energy": -340.61026425, "energy_zero": -340.59759584, "Eseg": -1.6183154099999228, "scf_steps": 62.0, "convergence": true, "element_count": 21, "potcar_electron_count": 8.0, "total_electron_count": 344.0, "method": "KP", "state": "Relaxed", "defect_type": "Substitutional", "dataset_case": "KP_Relaxed_Substitutional", "dataset_id": "fe_x_gb_kp_relaxed", "dataset_name": "Fe-X GB Segregation (KP, Relaxed)", "dataset_category": "Fe-X GB Segregation"}, {"job_name": "S11-RA110-S3-32-Sm-13", "GB": "S11-RA110-S3-32", "element": "Sm", "site": "13", "Z": 62, "n_Fe": 41, "n_Fe_diff": 0.0, "energy": -340.21520107, "energy_zero": -340.18874091, "Eseg": -1.2232522299999005, "scf_steps": 61.0, "convergence": true, "element_count": 28, "potcar_electron_count": 8.0, "total_electron_count": 344.0, "method": "KP", "state": "Relaxed", "defect_type": "Substitutional", "dataset_case": "KP_Relaxed_Substitutional", "dataset_id": "fe_x_gb_kp_relaxed", "dataset_name": "Fe-X GB Segregation (KP, Relaxed)", "dataset_category": "Fe-X GB Segregation"}, {"job_name": "S11-RA110-S3-32-Sm-17", "GB": "S11-RA110-S3-32", "element": "Sm", "site": "17", "Z": 62, "n_Fe": 41, "n_Fe_diff": 0.0, "energy": -341.20909105, "energy_zero": -341.20217847, "Eseg": -2.2171422099999063, "scf_steps": 70.0, "convergence": true, "element_count": 24, "potcar_electron_count": 8.0, "total_electron_count": 344.0, "method": "KP", "state": "Relaxed", "defect_type": "Substitutional", "dataset_case": "KP_Relaxed_Substitutional", "dataset_id": "fe_x_gb_kp_relaxed", "dataset_name": "Fe-X GB Segregation (KP, Relaxed)", "dataset_category": "Fe-X GB Segregation"}, {"job_name": "S11-RA110-S3-32-Sm-15", "GB": "S11-RA110-S3-32", "element": "Sm", "site": "15", "Z": 62, "n_Fe": 41, "n_Fe_diff": 0.0, "energy": -340.20200807, "energy_zero": -340.17346871, "Eseg": -1.2100592299998993, "scf_steps": 83.0, "convergence": true, "element_count": 26, "potcar_electron_count": 8.0, "total_electron_count": 344.0, "method": "KP", "state": "Relaxed", "defect_type": "Substitutional", "dataset_case": "KP_Relaxed_Substitutional", "dataset_id": "fe_x_gb_kp_relaxed", "dataset_name": "Fe-X GB Segregation (KP, Relaxed)", "dataset_category": "Fe-X GB Segregation"}, {"job_name": "S11-RA110-S3-32-Sm-19", "GB": "S11-RA110-S3-32", "element": "Sm", "site": "19", "Z": 62, "n_Fe": 41, "n_Fe_diff": 0.0, "energy": -341.21501393, "energy_zero": -341.20749562, "Eseg": -2.2230650899999205, "scf_steps": 59.0, "convergence": true, "element_count": 22, "potcar_electron_count": 8.0, "total_electron_count": 344.0, "method": "KP", "state": "Relaxed", "defect_type": "Substitutional", "dataset_case": "KP_Relaxed_Substitutional", "dataset_id": "fe_x_gb_kp_relaxed", "dataset_name": "Fe-X GB Segregation (KP, Relaxed)", "dataset_category": "Fe-X GB Segregation"}, {"job_name": "S11-RA110-S3-32-Sm-16", "GB": "S11-RA110-S3-32", "element": "Sm", "site": "16", "Z": 62, "n_Fe": 41, "n_Fe_diff": 0.0, "energy": -340.58993223, "energy_zero": -340.58385686, "Eseg": -1.5979833899999107, "scf_steps": 61.0, "convergence": true, "element_count": 25, "potcar_electron_count": 8.0, "total_electron_count": 344.0, "method": "KP", "state": "Relaxed", "defect_type": "Substitutional", "dataset_case": "KP_Relaxed_Substitutional", "dataset_id": "fe_x_gb_kp_relaxed", "dataset_name": "Fe-X GB Segregation (KP, Relaxed)", "dataset_category": "Fe-X GB Segregation"}, {"job_name": "S11-RA110-S3-32-Sm-21", "GB": "S11-RA110-S3-32", "element": "Sm", "site": "21", "Z": 62, "n_Fe": 41, "n_Fe_diff": 0.0, "energy": -340.62064135, "energy_zero": -340.60700397, "Eseg": -1.6286925099999507, "scf_steps": 66.0, "convergence": true, "element_count": 20, "potcar_electron_count": 8.0, "total_electron_count": 344.0, "method": "KP", "state": "Relaxed", "defect_type": "Substitutional", "dataset_case": "KP_Relaxed_Substitutional", "dataset_id": "fe_x_gb_kp_relaxed", "dataset_name": "Fe-X GB Segregation (KP, Relaxed)", "dataset_category": "Fe-X GB Segregation"}, {"job_name": "S11-RA110-S3-32-Sm-22", "GB": "S11-RA110-S3-32", "element": "Sm", "site": "22", "Z": 62, "n_Fe": 41, "n_Fe_diff": 0.0, "energy": -341.22005686, "energy_zero": -341.21246884, "Eseg": -2.2281080199999224, "scf_steps": 57.0, "convergence": true, "element_count": 19, "potcar_electron_count": 8.0, "total_electron_count": 344.0, "method": "KP", "state": "Relaxed", "defect_type": "Substitutional", "dataset_case": "KP_Relaxed_Substitutional", "dataset_id": "fe_x_gb_kp_relaxed", "dataset_name": "Fe-X GB Segregation (KP, Relaxed)", "dataset_category": "Fe-X GB Segregation"}, {"job_name": "S11-RA110-S3-32-Sm-14", "GB": "S11-RA110-S3-32", "element": "Sm", "site": "14", "Z": 62, "n_Fe": 41, "n_Fe_diff": 0.0, "energy": -340.62666386, "energy_zero": -340.62161216, "Eseg": -1.6347150199999305, "scf_steps": 74.0, "convergence": true, "element_count": 27, "potcar_electron_count": 8.0, "total_electron_count": 344.0, "method": "KP", "state": "Relaxed", "defect_type": "Substitutional", "dataset_case": "KP_Relaxed_Substitutional", "dataset_id": "fe_x_gb_kp_relaxed", "dataset_name": "Fe-X GB Segregation (KP, Relaxed)", "dataset_category": "Fe-X GB Segregation"}, {"job_name": "S3-RA110-S1-12-Sm-14", "GB": "S3-RA110-S1-12", "element": "Sm", "site": "14", "Z": 62, "n_Fe": 47, "n_Fe_diff": 0.0, "energy": -389.73675463, "energy_zero": -389.73203322, "Eseg": 0.04217049000004636, "scf_steps": 79.0, "convergence": true, "element_count": 33, "potcar_electron_count": 8.0, "total_electron_count": 392.0, "method": "KP", "state": "Relaxed", "defect_type": "Substitutional", "dataset_case": "KP_Relaxed_Substitutional", "dataset_id": "fe_x_gb_kp_relaxed", "dataset_name": "Fe-X GB Segregation (KP, Relaxed)", "dataset_category": "Fe-X GB Segregation"}, {"job_name": "S3-RA110-S1-12-Sm-18", "GB": "S3-RA110-S1-12", "element": "Sm", "site": "18", "Z": 62, "n_Fe": 47, "n_Fe_diff": 0.0, "energy": -389.7540049, "energy_zero": -389.74397574, "Eseg": 0.02492022000006955, "scf_steps": 74.0, "convergence": true, "element_count": 29, "potcar_electron_count": 8.0, "total_electron_count": 392.0, "method": "KP", "state": "Relaxed", "defect_type": "Substitutional", "dataset_case": "KP_Relaxed_Substitutional", "dataset_id": "fe_x_gb_kp_relaxed", "dataset_name": "Fe-X GB Segregation (KP, Relaxed)", "dataset_category": "Fe-X GB Segregation"}, {"job_name": "S3-RA110-S1-12-Sm-24", "GB": "S3-RA110-S1-12", "element": "Sm", "site": "24", "Z": 62, "n_Fe": 47, "n_Fe_diff": 0.0, "energy": -390.13815742, "energy_zero": -390.1258613, "Eseg": -0.35923229999997375, "scf_steps": 62.0, "convergence": true, "element_count": 23, "potcar_electron_count": 8.0, "total_electron_count": 392.0, "method": "KP", "state": "Relaxed", "defect_type": "Substitutional", "dataset_case": "KP_Relaxed_Substitutional", "dataset_id": "fe_x_gb_kp_relaxed", "dataset_name": "Fe-X GB Segregation (KP, Relaxed)", "dataset_category": "Fe-X GB Segregation"}, {"job_name": "S3-RA110-S1-12-Sm-20", "GB": "S3-RA110-S1-12", "element": "Sm", "site": "20", "Z": 62, "n_Fe": 47, "n_Fe_diff": 0.0, "energy": -390.00710606, "energy_zero": -389.99615948, "Eseg": -0.2281809399999588, "scf_steps": 61.0, "convergence": true, "element_count": 27, "potcar_electron_count": 8.0, "total_electron_count": 392.0, "method": "KP", "state": "Relaxed", "defect_type": "Substitutional", "dataset_case": "KP_Relaxed_Substitutional", "dataset_id": "fe_x_gb_kp_relaxed", "dataset_name": "Fe-X GB Segregation (KP, Relaxed)", "dataset_category": "Fe-X GB Segregation"}, {"job_name": "S3-RA110-S1-12-Sm-16", "GB": "S3-RA110-S1-12", "element": "Sm", "site": "16", "Z": 62, "n_Fe": 47, "n_Fe_diff": 0.0, "energy": -389.74914148, "energy_zero": -389.73690107, "Eseg": 0.02978364000006195, "scf_steps": 63.0, "convergence": true, "element_count": 31, "potcar_electron_count": 8.0, "total_electron_count": 392.0, "method": "KP", "state": "Relaxed", "defect_type": "Substitutional", "dataset_case": "KP_Relaxed_Substitutional", "dataset_id": "fe_x_gb_kp_relaxed", "dataset_name": "Fe-X GB Segregation (KP, Relaxed)", "dataset_category": "Fe-X GB Segregation"}, {"job_name": "S3-RA110-S1-12-Sm-22", "GB": "S3-RA110-S1-12", "element": "Sm", "site": "22", "Z": 62, "n_Fe": 47, "n_Fe_diff": 0.0, "energy": -390.11582952, "energy_zero": -390.10147059, "Eseg": -0.3369043999999235, "scf_steps": 57.0, "convergence": true, "element_count": 25, "potcar_electron_count": 8.0, "total_electron_count": 392.0, "method": "KP", "state": "Relaxed", "defect_type": "Substitutional", "dataset_case": "KP_Relaxed_Substitutional", "dataset_id": "fe_x_gb_kp_relaxed", "dataset_name": "Fe-X GB Segregation (KP, Relaxed)", "dataset_category": "Fe-X GB Segregation"}, {"job_name": "S3-RA110-S1-11-Sm-36", "GB": "S3-RA110-S1-11", "element": "Sm", "site": "36", "Z": 62, "n_Fe": 71, "n_Fe_diff": 0.0, "energy": -583.67855235, "energy_zero": -583.65528381, "Eseg": -1.516229929999895, "scf_steps": 64.0, "convergence": true, "element_count": 35, "potcar_electron_count": 8.0, "total_electron_count": 584.0, "method": "KP", "state": "Relaxed", "defect_type": "Substitutional", "dataset_case": "KP_Relaxed_Substitutional", "dataset_id": "fe_x_gb_kp_relaxed", "dataset_name": "Fe-X GB Segregation (KP, Relaxed)", "dataset_category": "Fe-X GB Segregation"}, {"job_name": "S3-RA110-S1-11-Sm-34", "GB": "S3-RA110-S1-11", "element": "Sm", "site": "34", "Z": 62, "n_Fe": 71, "n_Fe_diff": 0.0, "energy": -583.97772304, "energy_zero": -583.96374712, "Eseg": -1.8154006199998776, "scf_steps": 72.0, "convergence": true, "element_count": 37, "potcar_electron_count": 8.0, "total_electron_count": 584.0, "method": "KP", "state": "Relaxed", "defect_type": "Substitutional", "dataset_case": "KP_Relaxed_Substitutional", "dataset_id": "fe_x_gb_kp_relaxed", "dataset_name": "Fe-X GB Segregation (KP, Relaxed)", "dataset_category": "Fe-X GB Segregation"}, {"job_name": "S3-RA110-S1-11-Sm-28", "GB": "S3-RA110-S1-11", "element": "Sm", "site": "28", "Z": 62, "n_Fe": 71, "n_Fe_diff": 0.0, "energy": -582.0918971, "energy_zero": -582.08266002, "Eseg": 0.07042532000014035, "scf_steps": 56.0, "convergence": true, "element_count": 43, "potcar_electron_count": 8.0, "total_electron_count": 584.0, "method": "KP", "state": "Relaxed", "defect_type": "Substitutional", "dataset_case": "KP_Relaxed_Substitutional", "dataset_id": "fe_x_gb_kp_relaxed", "dataset_name": "Fe-X GB Segregation (KP, Relaxed)", "dataset_category": "Fe-X GB Segregation"}, {"job_name": "S3-RA110-S1-11-Sm-26", "GB": "S3-RA110-S1-11", "element": "Sm", "site": "26", "Z": 62, "n_Fe": 71, "n_Fe_diff": 0.0, "energy": -583.23406953, "energy_zero": -583.22662554, "Eseg": -1.071747109999933, "scf_steps": 62.0, "convergence": true, "element_count": 45, "potcar_electron_count": 8.0, "total_electron_count": 584.0, "method": "KP", "state": "Relaxed", "defect_type": "Substitutional", "dataset_case": "KP_Relaxed_Substitutional", "dataset_id": "fe_x_gb_kp_relaxed", "dataset_name": "Fe-X GB Segregation (KP, Relaxed)", "dataset_category": "Fe-X GB Segregation"}, {"job_name": "S3-RA110-S1-11-Sm-30", "GB": "S3-RA110-S1-11", "element": "Sm", "site": "30", "Z": 62, "n_Fe": 71, "n_Fe_diff": 0.0, "energy": -583.3614399, "energy_zero": -583.34400756, "Eseg": -1.1991174799999271, "scf_steps": 87.0, "convergence": true, "element_count": 41, "potcar_electron_count": 8.0, "total_electron_count": 584.0, "method": "KP", "state": "Relaxed", "defect_type": "Substitutional", "dataset_case": "KP_Relaxed_Substitutional", "dataset_id": "fe_x_gb_kp_relaxed", "dataset_name": "Fe-X GB Segregation (KP, Relaxed)", "dataset_category": "Fe-X GB Segregation"}, {"job_name": "S3-RA110-S1-11-Sm-32", "GB": "S3-RA110-S1-11", "element": "Sm", "site": "32", "Z": 62, "n_Fe": 71, "n_Fe_diff": 0.0, "energy": -583.58073719, "energy_zero": -583.57166463, "Eseg": -1.418414769999913, "scf_steps": 69.0, "convergence": true, "element_count": 39, "potcar_electron_count": 8.0, "total_electron_count": 584.0, "method": "KP", "state": "Relaxed", "defect_type": "Substitutional", "dataset_case": "KP_Relaxed_Substitutional", "dataset_id": "fe_x_gb_kp_relaxed", "dataset_name": "Fe-X GB Segregation (KP, Relaxed)", "dataset_category": "Fe-X GB Segregation"}, {"job_name": "S9-RA110-S2-21-Sm-35", "GB": "S9-RA110-S2-21", "element": "Sm", "site": "35", "Z": 62, "n_Fe": 67, "n_Fe_diff": 0.0, "energy": -552.65120303, "energy_zero": -552.64071561, "Eseg": -2.055068169999913, "scf_steps": 73.0, "convergence": true, "element_count": 32, "potcar_electron_count": 8.0, "total_electron_count": 552.0, "method": "KP", "state": "Relaxed", "defect_type": "Substitutional", "dataset_case": "KP_Relaxed_Substitutional", "dataset_id": "fe_x_gb_kp_relaxed", "dataset_name": "Fe-X GB Segregation (KP, Relaxed)", "dataset_category": "Fe-X GB Segregation"}, {"job_name": "S9-RA110-S2-21-Sm-28", "GB": "S9-RA110-S2-21", "element": "Sm", "site": "28", "Z": 62, "n_Fe": 67, "n_Fe_diff": 0.0, "energy": -552.79111064, "energy_zero": -552.78081296, "Eseg": -2.194975779999936, "scf_steps": 72.0, "convergence": true, "element_count": 39, "potcar_electron_count": 8.0, "total_electron_count": 552.0, "method": "KP", "state": "Relaxed", "defect_type": "Substitutional", "dataset_case": "KP_Relaxed_Substitutional", "dataset_id": "fe_x_gb_kp_relaxed", "dataset_name": "Fe-X GB Segregation (KP, Relaxed)", "dataset_category": "Fe-X GB Segregation"}, {"job_name": "S9-RA110-S2-21-Sm-26", "GB": "S9-RA110-S2-21", "element": "Sm", "site": "26", "Z": 62, "n_Fe": 67, "n_Fe_diff": 0.0, "energy": -550.70726708, "energy_zero": -550.69822998, "Eseg": -0.11113221999983125, "scf_steps": 68.0, "convergence": true, "element_count": 41, "potcar_electron_count": 8.0, "total_electron_count": 552.0, "method": "KP", "state": "Relaxed", "defect_type": "Substitutional", "dataset_case": "KP_Relaxed_Substitutional", "dataset_id": "fe_x_gb_kp_relaxed", "dataset_name": "Fe-X GB Segregation (KP, Relaxed)", "dataset_category": "Fe-X GB Segregation"}, {"job_name": "S9-RA110-S2-21-Sm-30", "GB": "S9-RA110-S2-21", "element": "Sm", "site": "30", "Z": 62, "n_Fe": 67, "n_Fe_diff": 0.0, "energy": -552.56834177, "energy_zero": -552.56079445, "Eseg": -1.9722069099998407, "scf_steps": 70.0, "convergence": true, "element_count": 37, "potcar_electron_count": 8.0, "total_electron_count": 552.0, "method": "KP", "state": "Relaxed", "defect_type": "Substitutional", "dataset_case": "KP_Relaxed_Substitutional", "dataset_id": "fe_x_gb_kp_relaxed", "dataset_name": "Fe-X GB Segregation (KP, Relaxed)", "dataset_category": "Fe-X GB Segregation"}, {"job_name": "S9-RA110-S2-21-Sm-29", "GB": "S9-RA110-S2-21", "element": "Sm", "site": "29", "Z": 62, "n_Fe": 67, "n_Fe_diff": 0.0, "energy": -553.21814117, "energy_zero": -553.21211162, "Eseg": -2.622006309999847, "scf_steps": 75.0, "convergence": true, "element_count": 38, "potcar_electron_count": 8.0, "total_electron_count": 552.0, "method": "KP", "state": "Relaxed", "defect_type": "Substitutional", "dataset_case": "KP_Relaxed_Substitutional", "dataset_id": "fe_x_gb_kp_relaxed", "dataset_name": "Fe-X GB Segregation (KP, Relaxed)", "dataset_category": "Fe-X GB Segregation"}, {"job_name": "S9-RA110-S2-21-Sm-34", "GB": "S9-RA110-S2-21", "element": "Sm", "site": "34", "Z": 62, "n_Fe": 67, "n_Fe_diff": 0.0, "energy": -553.25204837, "energy_zero": -553.24602869, "Eseg": -2.655913509999891, "scf_steps": 76.0, "convergence": true, "element_count": 33, "potcar_electron_count": 8.0, "total_electron_count": 552.0, "method": "KP", "state": "Relaxed", "defect_type": "Substitutional", "dataset_case": "KP_Relaxed_Substitutional", "dataset_id": "fe_x_gb_kp_relaxed", "dataset_name": "Fe-X GB Segregation (KP, Relaxed)", "dataset_category": "Fe-X GB Segregation"}, {"job_name": "S9-RA110-S2-21-Sm-27", "GB": "S9-RA110-S2-21", "element": "Sm", "site": "27", "Z": 62, "n_Fe": 67, "n_Fe_diff": 0.0, "energy": -551.06432516, "energy_zero": -551.05082084, "Eseg": -0.46819029999983286, "scf_steps": 77.0, "convergence": true, "element_count": 40, "potcar_electron_count": 8.0, "total_electron_count": 552.0, "method": "KP", "state": "Relaxed", "defect_type": "Substitutional", "dataset_case": "KP_Relaxed_Substitutional", "dataset_id": "fe_x_gb_kp_relaxed", "dataset_name": "Fe-X GB Segregation (KP, Relaxed)", "dataset_category": "Fe-X GB Segregation"}, {"job_name": "S9-RA110-S2-21-Sm-31", "GB": "S9-RA110-S2-21", "element": "Sm", "site": "31", "Z": 62, "n_Fe": 67, "n_Fe_diff": 0.0, "energy": -552.66545865, "energy_zero": -552.65661536, "Eseg": -2.069323789999885, "scf_steps": 79.0, "convergence": true, "element_count": 36, "potcar_electron_count": 8.0, "total_electron_count": 552.0, "method": "KP", "state": "Relaxed", "defect_type": "Substitutional", "dataset_case": "KP_Relaxed_Substitutional", "dataset_id": "fe_x_gb_kp_relaxed", "dataset_name": "Fe-X GB Segregation (KP, Relaxed)", "dataset_category": "Fe-X GB Segregation"}, {"job_name": "S9-RA110-S2-21-Sm-33", "GB": "S9-RA110-S2-21", "element": "Sm", "site": "33", "Z": 62, "n_Fe": 67, "n_Fe_diff": 0.0, "energy": -551.78035435, "energy_zero": -551.7571637, "Eseg": -1.1842194899999186, "scf_steps": 72.0, "convergence": true, "element_count": 34, "potcar_electron_count": 8.0, "total_electron_count": 552.0, "method": "KP", "state": "Relaxed", "defect_type": "Substitutional", "dataset_case": "KP_Relaxed_Substitutional", "dataset_id": "fe_x_gb_kp_relaxed", "dataset_name": "Fe-X GB Segregation (KP, Relaxed)", "dataset_category": "Fe-X GB Segregation"}, {"job_name": "S9-RA110-S2-21-Sm-36", "GB": "S9-RA110-S2-21", "element": "Sm", "site": "36", "Z": 62, "n_Fe": 67, "n_Fe_diff": 0.0, "energy": -550.66786432, "energy_zero": -550.64813048, "Eseg": -0.07172945999991498, "scf_steps": 124.0, "convergence": true, "element_count": 31, "potcar_electron_count": 8.0, "total_electron_count": 552.0, "method": "KP", "state": "Relaxed", "defect_type": "Substitutional", "dataset_case": "KP_Relaxed_Substitutional", "dataset_id": "fe_x_gb_kp_relaxed", "dataset_name": "Fe-X GB Segregation (KP, Relaxed)", "dataset_category": "Fe-X GB Segregation"}]